LICENSE
README.md
setup.py
pyAMOSA.egg-info/PKG-INFO
pyAMOSA.egg-info/SOURCES.txt
pyAMOSA.egg-info/dependency_links.txt
pyAMOSA.egg-info/requires.txt
pyAMOSA.egg-info/top_level.txt
pyamosa/CombinedStopCriterion.py
pyamosa/Config.py
pyamosa/DataType.py
pyamosa/DifferentialVariableGrouping2.py
pyamosa/DynamicRandomGroupingOptimizer.py
pyamosa/GenericGroupingOptimizer.py
pyamosa/MultiFileCacheHandle.py
pyamosa/Optimizer.py
pyamosa/Pareto.py
pyamosa/Problem.py
pyamosa/StochasticHillClimbing.py
pyamosa/StopCriterion.py
pyamosa/StopMaxTime.py
pyamosa/StopMinTemperature.py
pyamosa/StopPhyWindow.py
pyamosa/VariableGrouping.py
pyamosa/__init__.py