Metadata-Version: 2.1
Name: pyAMOSA
Version: 2.0.2
Summary: Python implementation of the Archived Multi-Objective Simulated Annealing optimization heuristic
Home-page: https://github.com/SalvatoreBarone/pyAMOSA
Author: Salvatore Barone
Author-email: salvatore.barone@unina.it
Project-URL: Bug Reports, https://github.com/SalvatoreBarone/pyAMOSA/issues
Project-URL: Source, https://github.com/SalvatoreBarone/pyAMOSA
Keywords: Multi Objective Optimization
Classifier: Intended Audience :: Information Technology
Classifier: Intended Audience :: Science/Research
Classifier: Topic :: Scientific/Engineering
Classifier: License :: OSI Approved :: GNU General Public License v3 or later (GPLv3+)
Classifier: Programming Language :: Python :: 3.9
License-File: LICENSE
